kivygui/__init__.py
kivygui/_config.py
kivygui/cmdpane.py
kivygui/editor.py
kivygui/keybinder.py
kivygui/rules.py
kivygui/settings.py
kivygui/splash.py
kivygui/statusbar.py
kivygui/toplevel.py
kivygui/util.py
kivygui/workbench.py
kivygui/cmdpane_elements/__init__.py
kivygui/cmdpane_elements/workbook_create.py
kivygui/presenter/__init__.py
kivygui/presenter/requests.py
kivygui/presenter/responses.py
uncrumpled_kivygui-0.1.0.dist-info/DESCRIPTION.rst
uncrumpled_kivygui-0.1.0.dist-info/METADATA
uncrumpled_kivygui-0.1.0.dist-info/RECORD
uncrumpled_kivygui-0.1.0.dist-info/WHEEL
uncrumpled_kivygui-0.1.0.dist-info/metadata.json
uncrumpled_kivygui-0.1.0.dist-info/top_level.txt
