Metadata-Version: 2.0
Name: uncrumpled-kivygui
Version: 0.1.0
Summary: kivygui for uncrumpled
Home-page: UNKNOWN
Author: tmothy eichler
Author-email: tim_eichler@hotmail.com
License: BSD
Keywords: uncrumpled gui kivy ui
Platform: UNKNOWN
Classifier: Development Status :: 3 - Alpha
Classifier: Intended Audience :: Developers
Classifier: License :: OSI Approved :: BSD License
Classifier: Programming Language :: Python :: 3
